{
    "video_id": "3JmfRxmnmtA",
    "cover_url": "https://i.ytimg.com/vi/3JmfRxmnmtA/maxresdefault.jpg",
    "filename": "3JmfRxmnmtA.jpg",
    "category": "People & Blogs",
    "date": "2020-05-11",
    "permalink": "https://www.youtube.com/watch?v=3JmfRxmnmtA",
    "description": "2. \ud835\udc11\ud835\udc00\ud835\udc02\ud835\udc02\ud835\udc0e\ud835\udc0d\ud835\udc13\ud835\udc08 \ud835\udc03\u2019\ud835\udc00\ud835\udc11\ud835\udc02\ud835\udc07\ud835\udc08\ud835\udc15\ud835\udc08\ud835\udc0e. \ud835\udc12\ud835\udc00\ud835\udc0d\ud835\udc13\ud835\udc00 \ud835\udc06\ud835\udc08\ud835\udc14\ud835\udc0b\ud835\udc08\ud835\udc00 | W L'Italia! dal dominio Austriaco al Regno d'Italia",
    "tags": [
        "FONDAZIONE BRESCIA MUSEI"
    ],
    "week": "20",
    "year": "2020"
}